pydineof/__about__.py
pydineof/__init__.py
pydineof/cli.py
pydineof/main.py
pydineof-0.1.1.dist-info/METADATA
pydineof-0.1.1.dist-info/WHEEL
pydineof-0.1.1.dist-info/entry_points.txt
pydineof-0.1.1.dist-info/licenses/LICENSE
pydineof-0.1.1.dist-info/RECORD
