Metadata-Version: 2.4
Name: pyDINEOF
Version: 0.1.1
Summary: A Python version of DINEOF.
Project-URL: Documentation, https://github.com/acoque/pyDINEOF#readme
Project-URL: Issues, https://github.com/acoque/pyDINEOF/issues
Project-URL: Source, https://github.com/acoque/pyDINEOF
Author: Arthur Coqué
Maintainer-email: Arthur Coqué <arthur.coque@naturalsciences.be>
License-Expression: GPL-3.0-or-later
License-File: LICENSE
Classifier: Development Status :: 4 - Beta
Classifier: Intended Audience :: Science/Research
Classifier: License :: OSI Approved :: GNU General Public License v3 or later (GPLv3+)
Classifier: Programming Language :: Python
Classifier: Programming Language :: Python :: 3.10
Classifier: Programming Language :: Python :: 3.11
Classifier: Programming Language :: Python :: 3.12
Classifier: Topic :: Scientific/Engineering :: Atmospheric Science
Classifier: Topic :: Scientific/Engineering :: Image Processing
Classifier: Topic :: Scientific/Engineering :: Oceanography
Classifier: Typing :: Typed
Requires-Python: >=3.10
Requires-Dist: numpy
Requires-Dist: pandas
Requires-Dist: scipy
Requires-Dist: xarray
